gdalTools/__init__.py
gdalTools/rasterConversion.py
gdalTools/rasterTools.py
gdalTools/shpConversion.py
gdalTools/shpTools.py
gdalTools-1.5.dist-info/LICENSE.txt
gdalTools-1.5.dist-info/METADATA
gdalTools-1.5.dist-info/WHEEL
gdalTools-1.5.dist-info/top_level.txt
gdalTools-1.5.dist-info/RECORD
