Metadata-Version: 2.1
Name: gdalTools
Version: 1.5
Summary: some useful tools in gdal
Home-page: https://github.com/SonwYang/gdaltools.git
Author: yang peng
Author-email: 1224425503@qq.com
License: UNKNOWN
Platform: UNKNOWN
Classifier: Programming Language :: Python :: 3
Classifier: License :: OSI Approved :: MIT License
Classifier: Operating System :: OS Independent
License-File: LICENSE.txt
Requires-Dist: gdal (>=3.0.1)
Requires-Dist: geopandas (>=0.8.2)
Requires-Dist: rasterio (>=1.2.0)
Requires-Dist: Fiona (>=1.8.18)
Requires-Dist: rasterstats (>=0.15.0)
